ValorantHeadhunterPy
