Metadata-Version: 2.1
Name: valorantheadhunterapipy
Version: 1.2
Summary: Somente testes
Home-page: https://github.com/OnlyTH777/VALORANT-Headhunter.py
Author: OnlyTH
License: MIT License
License-File: LICENSE.txt
